frixa_anitrack/__init__.py
frixa_anitrack/main.py
frixa_anitrack/styles.tcss
frixa_anitrack-0.2.2.dist-info/METADATA
frixa_anitrack-0.2.2.dist-info/WHEEL
frixa_anitrack-0.2.2.dist-info/entry_points.txt
frixa_anitrack-0.2.2.dist-info/RECORD
