Metadata-Version: 2.4
Name: frixa-anitrack
Version: 0.2.2
Summary: Add your description here
Author-email: frixaco <rustam21ashurmatov@gmail.com>
Requires-Python: >=3.13
Requires-Dist: aiohttp>=3.12.13
Requires-Dist: selectolax>=0.3.31
Requires-Dist: textual-dev>=1.7.0
Requires-Dist: textual[syntax]>=3.5.0
